MANIFEST.in
README.md
setup.py
hilandBasicLibrary/.env.default
hilandBasicLibrary/README.md
hilandBasicLibrary/__init__.py
hilandBasicLibrary/__projectConfig.ini
hilandBasicLibrary/__projectHelper.py
hilandBasicLibrary/configHelper.py
hilandBasicLibrary/enums.py
hilandBasicLibrary/projectHelper.py
hilandBasicLibrary.egg-info/PKG-INFO
hilandBasicLibrary.egg-info/SOURCES.txt
hilandBasicLibrary.egg-info/dependency_links.txt
hilandBasicLibrary.egg-info/top_level.txt
hilandBasicLibrary/biz/__init__.py
hilandBasicLibrary/biz/stockHelper.py
hilandBasicLibrary/biz/tencentHelper.py
hilandBasicLibrary/data/__init__.py
hilandBasicLibrary/data/collectionHelper.py
hilandBasicLibrary/data/dateTimeHelper.py
hilandBasicLibrary/data/dictHelper.py
hilandBasicLibrary/data/htmlHelper.py
hilandBasicLibrary/data/listHelper.py
hilandBasicLibrary/data/numberHelper.py
hilandBasicLibrary/data/objectHelper.py
hilandBasicLibrary/data/pandasHelper.py
hilandBasicLibrary/data/randomHelper.py
hilandBasicLibrary/data/reflectHelper.py
hilandBasicLibrary/data/regexHelper.py
hilandBasicLibrary/data/setHelper.py
hilandBasicLibrary/data/stringHelper.py
hilandBasicLibrary/dataBase/__init__.py
hilandBasicLibrary/dataBase/databaseClient.py
hilandBasicLibrary/dataBase/databaseDDL.py
hilandBasicLibrary/dataBase/databaseEnum.py
hilandBasicLibrary/dataBase/databaseHelper.py
hilandBasicLibrary/dataBase/databaseMate.py
hilandBasicLibrary/dataBase/databaseUnitTest.py
hilandBasicLibrary/dataBase/MongoDB/__init__.py
hilandBasicLibrary/dataBase/MongoDB/ddl.py
hilandBasicLibrary/dataBase/MongoDB/helper.py
hilandBasicLibrary/dataBase/MongoDB/mate.py
hilandBasicLibrary/dataBase/MySql/__init__.py
hilandBasicLibrary/dataBase/MySql/ddl.py
hilandBasicLibrary/dataBase/MySql/mate.py
hilandBasicLibrary/dataBase/MySql/pool.py
hilandBasicLibrary/environment/__init__.py
hilandBasicLibrary/environment/consoleHelper.py
hilandBasicLibrary/environment/envHelper.py
hilandBasicLibrary/io/__init__.py
hilandBasicLibrary/io/dirHelper.py
hilandBasicLibrary/io/fileHelper.py
hilandBasicLibrary/io/ioHelper.py
hilandBasicLibrary/io/pathHelper.py
hilandBasicLibrary/model/__init__.py
