Metadata-Version: 2.1
Name: hilandBasicLibrary
Version: 0.4.20
Summary: 企业级的 PYTHON 库.
Home-page: https://github.com/notinmood/BasicLibrary.PY
Author: xiedali
Author-email: 9727005@qq.com
License: MIT
Platform: UNKNOWN
Classifier: License :: OSI Approved :: MIT License
Classifier: Programming Language :: Python
Classifier: Programming Language :: Python :: 3
Classifier: Programming Language :: Python :: 3.6
Classifier: Programming Language :: Python :: Implementation :: CPython
Classifier: Programming Language :: Python :: Implementation :: PyPy
Requires-Python: >=3.6.0
